./.gitignore
./.python-version
./Dockerfile
./LICENSE
./MANIFEST.in
./PKG-INFO
./README.md
./__init__.py
./bailian_mcpserver.py
./docker-compose.yml.example
./pyproject.toml
./tests/final_verify.py
bailian_imagegen_mcp_edited-0.1.6.dist-info/METADATA
bailian_imagegen_mcp_edited-0.1.6.dist-info/WHEEL
bailian_imagegen_mcp_edited-0.1.6.dist-info/entry_points.txt
bailian_imagegen_mcp_edited-0.1.6.dist-info/licenses/LICENSE
bailian_imagegen_mcp_edited-0.1.6.dist-info/RECORD
