Metadata-Version: 2.4
Name: bailian-imagegen-mcp-edited
Version: 0.1.6
Summary: Aliyun Bailian Image Generation MCP Server
License-File: LICENSE
Requires-Python: >=3.10
Requires-Dist: httpx>=0.20.0
Requires-Dist: mcp[cli]>=0.1.0
Requires-Dist: starlette>=0.20.0
Requires-Dist: uvicorn>=0.20.0
